Velkoz/__init__.py
Velkoz/settings.py
Velkoz/setup.py
Velkoz/velkoz.py
Velkoz/data/__init__.py
Velkoz/data/champion.py
Velkoz/data/common.py
Velkoz/eye/__init__.py
Velkoz/eye/account.py
Velkoz/eye/champion_mastery.py
Velkoz/eye/common.py
Velkoz/eye/match.py
Velkoz/eye/summoner.py
Velkoz/supp/__init__.py
Velkoz/supp/account.py
Velkoz/supp/champion.py
Velkoz/supp/champion_mastery.py
Velkoz/supp/match.py
Velkoz/supp/summoner.py
Velkoz/tentacles/__init__.py
Velkoz/tentacles/account.py
Velkoz/tentacles/api.py
Velkoz/tentacles/champion_mastery.py
Velkoz/tentacles/common.py
Velkoz/tentacles/config.py
Velkoz/tentacles/match.py
Velkoz/tentacles/summoner.py
Velkoz-0.1.0.dist-info/METADATA
Velkoz-0.1.0.dist-info/WHEEL
Velkoz-0.1.0.dist-info/top_level.txt
Velkoz-0.1.0.dist-info/RECORD
